{
  "name": "RSI 반전 기본",
  "strategy_type": "rsi_reversion",
  "universe": [
    ".SPY",
    ".QQQ",
    ".AAPL"
  ],
  "timeframe": "15Min",
  "params": {
    "low_th": 30,
    "high_th": 70
  },
  "risk": {
    "max_notional_per_symbol": 2000,
    "max_positions": 5,
    "stop_loss_pct": 0.05,
    "take_profit_pct": 0.1
  },
  "order": {
    "type": "limit",
    "limit_slippage_pct": 0.002,
    "time_in_force": "day"
  },
  "rebalance": {
    "interval": "1h"
  },
  "extended_hours": false,
  "enabled": true
}